topsis/__init__.py
topsis/__main__.py
topsis_chirag_102103278-1.0.4.dist-info/LICENSE
topsis_chirag_102103278-1.0.4.dist-info/METADATA
topsis_chirag_102103278-1.0.4.dist-info/WHEEL
topsis_chirag_102103278-1.0.4.dist-info/entry_points.txt
topsis_chirag_102103278-1.0.4.dist-info/top_level.txt
topsis_chirag_102103278-1.0.4.dist-info/RECORD
