Metadata-Version: 2.1
Name: topsis_chirag_102103278
Version: 1.0.4
Summary: A Python package to find TOPSIS for MCDM (Multi-Criteria Decision Analysis Method)
Author: Chirag Gupta
Author-email: chirag1044gupta@gmail.com
License: MIT
Keywords: TOPSIS,MCDM
Classifier: Development Status :: 5 - Production/Stable
Classifier: Intended Audience :: Developers
Classifier: Topic :: Software Development :: Build Tools
Classifier: License :: OSI Approved :: MIT License
Classifier: Programming Language :: Python :: 3
License-File: LICENSE
Requires-Dist: numpy
Requires-Dist: pandas
Requires-Dist: sys
